setup.py
distri_prob/Binomialdistribution.py
distri_prob/Gaussiandistribution.py
distri_prob/Generaldistribution.py
distri_prob/__init__.py
distri_prob.egg-info/PKG-INFO
distri_prob.egg-info/SOURCES.txt
distri_prob.egg-info/dependency_links.txt
distri_prob.egg-info/not-zip-safe
distri_prob.egg-info/top_level.txt