Metadata-Version: 1.0
Name: distri-prob
Version: 1.2
Summary: Gaussian and Binomial distributions
Home-page: UNKNOWN
Author: Naruto Uzumaki
Author-email: narutouzumaki@konoha.com
License: UNKNOWN
Platform: UNKNOWN
